inferploidy/__init__.py
inferploidy/clustering.py
inferploidy/inferploidy.py
inferploidy/load_data.py
inferploidy/default_optional_files/hg38_gene_only.gtf
inferploidy/default_optional_files/mm10_gene_only.gtf
inferploidy-0.3.3.dist-info/licenses/LICENSE
inferploidy-0.3.3.dist-info/METADATA
inferploidy-0.3.3.dist-info/WHEEL
inferploidy-0.3.3.dist-info/entry_points.txt
inferploidy-0.3.3.dist-info/top_level.txt
inferploidy-0.3.3.dist-info/RECORD
