Metadata-Version: 2.4
Name: inferploidy
Version: 0.3.3
Summary: Tookits for Tumor cell identification in single-cell RNA-seq data
Author-email: Seokhyun Yoon <syoon@dku.edu>
License: MIT License
Project-URL: Homepage, https://github.com/combio-dku
Keywords: single-cell omics,bioinformatics
Classifier: Programming Language :: Python
Classifier: Programming Language :: Python :: 3
License-File: LICENSE
Provides-Extra: dev
Requires-Dist: numpy; extra == "dev"
Requires-Dist: pandas; extra == "dev"
Requires-Dist: scipy; extra == "dev"
Requires-Dist: scikit-learn; extra == "dev"
Requires-Dist: scikit-network; extra == "dev"
Requires-Dist: infercnvpy; extra == "dev"
Requires-Dist: scanpy; extra == "dev"
Requires-Dist: seaborn; extra == "dev"
Dynamic: license-file
